XMLegant.py
setup.py
XMLegant.egg-info/PKG-INFO
XMLegant.egg-info/SOURCES.txt
XMLegant.egg-info/dependency_links.txt
XMLegant.egg-info/top_level.txt