Metadata-Version: 1.0
Name: XMLegant
Version: 0.8.1
Summary: A class allowing easy XML generation
Home-page: http://xmlegant.from.bz
Author: Bill Zeller
Author-email: billiam@gmail.com
License: BSD
Platform: UNKNOWN
Classifier: Development Status :: 3 - Alpha
Classifier: Intended Audience :: Developers
Classifier: License :: OSI Approved :: BSD License
Classifier: Operating System :: OS Independent
Classifier: Programming Language :: Python
Classifier: Programming Language :: Python :: 2.5
Classifier: Topic :: Software Development :: Libraries :: Python Modules
Classifier: Topic :: Text Processing :: Markup :: XML
